Metadata-Version: 2.1
Name: besca
Version: 2.5.5
Summary: Collection of BEDA internal python functions for analysing single cell RNAseq data.
Home-page: https://github.com/bedapub/besca
Author: BEDA community
Author-email: manuel.kohler@roche.com
License: GPLv3
Platform: UNKNOWN
Classifier: Development Status :: 5 - Production/Stable
Classifier: Intended Audience :: Developers
Classifier: Topic :: Software Development :: Build Tools
Classifier: License :: OSI Approved :: GNU General Public License v3 (GPLv3)
Classifier: Programming Language :: Python :: 3
Classifier: Programming Language :: Python :: 3.8
Requires-Dist: scipy>=1.5.4
Requires-Dist: flask-restful
Requires-Dist: dominate
Requires-Dist: requests
Requires-Dist: numpy>=1.18.0
Requires-Dist: scanpy>=1.7.2
Requires-Dist: plotly
Requires-Dist: anndata>=0.7.4
Requires-Dist: seaborn
Requires-Dist: mygene
Requires-Dist: pandas>=1.1.0
Requires-Dist: matplotlib>=3.5.0
Requires-Dist: bbknn
Requires-Dist: ipython
Requires-Dist: nbclean
Requires-Dist: scikit-learn>=1.0.2
Requires-Dist: python-igraph
Requires-Dist: leidenalg>=0.8.3
Requires-Dist: scanorama
Requires-Dist: scvelo
Requires-Dist: umap-learn
Requires-Dist: session-info
Requires-Dist: pydot
Requires-Dist: scvi-tools
Requires-Dist: pytest
Requires-Dist: deprecation
Requires-Dist: gseapy
